db_queries_bulk_migrator/__init__.py
db_queries_bulk_migrator/db_conversion.py
db_queries_bulk_migrator/main.py
db_queries_bulk_migrator/models.py
db_queries_bulk_migrator/utils.py
db_queries_bulk_migrator-0.3.1.dist-info/entry_points.txt
db_queries_bulk_migrator-0.3.1.dist-info/METADATA
db_queries_bulk_migrator-0.3.1.dist-info/WHEEL
db_queries_bulk_migrator-0.3.1.dist-info/RECORD
