Metadata-Version: 2.1
Name: db-queries-bulk-migrator
Version: 0.3.1
Summary: 
Author: Your Name
Author-email: you@example.com
Requires-Python: >=3.10,<4.0
Classifier: Programming Language :: Python :: 3
Classifier: Programming Language :: Python :: 3.10
Classifier: Programming Language :: Python :: 3.11
Classifier: Programming Language :: Python :: 3.12
Requires-Dist: dt (>=1.1.67,<2.0.0)
Requires-Dist: dt-cli (>=1.6.19,<2.0.0)
Requires-Dist: openpyxl (>=3.1.5,<4.0.0)
Requires-Dist: pandas (>=2.2.3,<3.0.0)
Requires-Dist: pymmh3 (>=0.0.5,<0.0.6)
Requires-Dist: pyyaml (>=6.0.2,<7.0.0)
Requires-Dist: regex (>=2024.9.11,<2025.0.0)
Requires-Dist: rich (>=13.8.1,<14.0.0)
Requires-Dist: ruamel-yaml (>=0.18.6,<0.19.0)
Requires-Dist: sqlglot (>=25.23.0,<26.0.0)
Requires-Dist: sqlparse (>=0.5.1,<0.6.0)
Requires-Dist: typer (>=0.12.5,<0.13.0)
Requires-Dist: xlsxwriter (>=3.2.0,<4.0.0)
